{
  "config": {
    "features": [
      {
        "feature": {
          "config": {
            "to_place": {
              "state": {
                "Properties": {
                  "mode": "static",
                  "facing": "north"
                },
                "Name": "moyai:moyai"
              },
              "type": "minecraft:simple_state_provider"
            }
          },
          "type": "minecraft:simple_block"
        },
        "placement": [
          {
            "predicate": {
              "state": {
                "Properties": {
                  "mode": "static",
                  "facing": "north"
                },
                "Name": "moyai:moyai"
              },
              "type": "minecraft:would_survive"
            },
            "type": "minecraft:block_predicate_filter"
          }
        ]
      },
      {
        "feature": {
          "config": {
            "to_place": {
              "state": {
                "Properties": {
                  "mode": "static",
                  "facing": "south"
                },
                "Name": "moyai:moyai"
              },
              "type": "minecraft:simple_state_provider"
            }
          },
          "type": "minecraft:simple_block"
        },
        "placement": [
          {
            "predicate": {
              "state": {
                "Properties": {
                  "mode": "static",
                  "facing": "south"
                },
                "Name": "moyai:moyai"
              },
              "type": "minecraft:would_survive"
            },
            "type": "minecraft:block_predicate_filter"
          }
        ]
      },
      {
        "feature": {
          "config": {
            "to_place": {
              "state": {
                "Properties": {
                  "mode": "static",
                  "facing": "east"
                },
                "Name": "moyai:moyai"
              },
              "type": "minecraft:simple_state_provider"
            }
          },
          "type": "minecraft:simple_block"
        },
        "placement": [
          {
            "predicate": {
              "state": {
                "Properties": {
                  "mode": "static",
                  "facing": "east"
                },
                "Name": "moyai:moyai"
              },
              "type": "minecraft:would_survive"
            },
            "type": "minecraft:block_predicate_filter"
          }
        ]
      },
      {
        "feature": {
          "config": {
            "to_place": {
              "state": {
                "Properties": {
                  "mode": "static",
                  "facing": "west"
                },
                "Name": "moyai:moyai"
              },
              "type": "minecraft:simple_state_provider"
            }
          },
          "type": "minecraft:simple_block"
        },
        "placement": [
          {
            "predicate": {
              "state": {
                "Properties": {
                  "mode": "static",
                  "facing": "west"
                },
                "Name": "moyai:moyai"
              },
              "type": "minecraft:would_survive"
            },
            "type": "minecraft:block_predicate_filter"
          }
        ]
      }
    ]
  },
  "type": "minecraft:simple_random_selector"
}